<?xml version="1.0" encoding="UTF-8"?>
<h1:DocumentSet xmlns:h1="http://www.startext.de/HiDA/DefService/XMLSchema">
    <h1:ContentInfo>
        <h1:Format>HIDA-DOC1-XML</h1:Format>
        <h1:CreationDate>16.08.2023 15:39:37:569</h1:CreationDate>
    </h1:ContentInfo>
    <h1:Document DocKey="obj     32595133" FieldsCount="61">
        <h1:Block Type="obj" CreationDate="05.01.2022 11:05:01" CreatorID="Admin" ChangeDate="05.01.2022 11:08:38" ChangerID="hab" OwnerID="hab" FieldsCount="34">
            <h1:Field Type="5000" Value="32595133"/>
            <h1:Field Type="bezsoz" Value="Verwaltung">
                <h1:Field Type="4564" Value="Luxemburg (Stadt)"/>
                <h1:Field Type="4600" Value="Archives diocésaines de Luxembourg"/>
                <h1:Field Type="4500" Value="30003532"/>
                <h1:Field Type="4502norm" Value="1230022287"/>
                <h1:Field Type="4503norm" Value="LU-DAL"/>
                <h1:Field Type="4650" Value="Pfarrarchiv Luxemburg - Notre-Dame 159* Reg"/>
                <h1:Field Type="4650vt" Value="Pfarrarchiv Luxemburg - Notre-Dame 159* Reg"/>
            </h1:Field>
            <h1:Field Type="4643" Value="Pfarrarchiv Luxemburg"/>
            <h1:Field Type="4645" Value="Notre-Dame 159* Reg"/>
            <h1:Field Type="5209vt" Value="Syntagma epitomicum"/>
            <h1:Field Type="5209norm" Value="Syntagma epitomicum"/>
            <h1:Field Type="5230" Value="Handschrift &amp; Image-Nachweis - Bisher leider keine Daten vorhanden"/>
            <h1:Field Type="5210norm" Value="vorhanden"/>
            <h1:Field Type="5240vt" Value="Codex"/>
            <h1:Field Type="5240norm" Value="Codex"/>
            <h1:Field Type="5060vt" Value="Datierung">
                <h1:Field Type="5064vt" Value="17. Jh. Mitte"/>
            </h1:Field>
            <h1:Field Type="5060norm" Value="Datierung">
                <h1:Field Type="5064norm" Value="17. Jh., Mitte"/>
                <h1:Field Type="5071norm" Value="1646"/>
                <h1:Field Type="5077norm" Value="1655"/>
            </h1:Field>
            <h1:Field Type="5130vt" Value="Echternach"/>
            <h1:Field Type="5130norm" Value="Echternach">
                <h1:Field Type="5131norm" Value="4013481-7"/>
                <h1:Field Type="5132norm" Value="2960630"/>
                <h1:Field Type="5133norm" Value="7012312"/>
            </h1:Field>
            <h1:Field Type="9951norm" Value="Beschreibung">
                <h1:Field Type="9952norm" Value="Thomas Falmagne"/>
                <h1:Field Type="9953norm" Value="2009"/>
            </h1:Field>
            <h1:Field Type="5260vt" Value="Papier"/>
            <h1:Field Type="5260norm" Value="Papier"/>
            <h1:Field Type="5360vt" Value="14,5 x 10 (cm)"/>
            <h1:Field Type="5360norm" Value="14,5 × 10">
                <h1:Field Type="5361norm" Value="14,5"/>
                <h1:Field Type="5362norm" Value="10"/>
                <h1:Field Type="5364norm" Value="real"/>
            </h1:Field>
            <h1:Field Type="5382norm" Value="ERRECHNET: Oktav"/>
            <h1:Field Type="5382norm" Value="ERRECHNET: kleiner als Oktav"/>
            <h1:Field Type="5706vt" Value="28 (Blatt)"/>
            <h1:Field Type="5706norm" Value="28 Bl."/>
            <h1:Field Type="5706rech" Value="28"/>
            <h1:Field Type="5710norm" Value="lateinisch"/>
            <h1:Field Type="bezlit" Value="Katalogtext">
                <h1:Field Type="8330" Value="Luxemburg BN Kat. 1.2"/>
            </h1:Field>
            <h1:Field Type="8265" Value="FALMAGNE, Thomas unter Mitwirkung von Luc DEITZ: Die Echternacher Handschriften bis zum Jahr 1628 in den Beständen der Bibliothèque Nationale de Luxembourg sowie der Archives diocésaines de Luxembourg, der Archives nationales, der Section historique de l'Institut grand-ducal und des Grand Séminaire de Luxembourg. Teil 2: Beschreibungen und Register. - Wiesbaden: Harrassowitz, 2009. - (Die Handschriften der Bibliothèque Nationale de Luxembourg; 1,2)"/>
            <h1:Field Type="8440norm" Value="Anfang">
                <h1:Field Type="8441norm" Value="536"/>
                <h1:Field Type="8442norm" Value="3"/>
                <h1:Field Type="8443norm" Value="Page536_Block3"/>
            </h1:Field>
            <h1:Field Type="8440norm" Value="Ende">
                <h1:Field Type="8441norm" Value="538"/>
                <h1:Field Type="8442norm" Value="4"/>
                <h1:Field Type="8443norm" Value="Page538_Block4"/>
            </h1:Field>
            <h1:Field Type="8450" Value="RETROKatalog">
                <h1:Field Type="8540" Value="LUX_DioezesanA_Kat_1_2"/>
            </h1:Field>
            <h1:Field Type="99hs" Value="Retrokonversionsdokument"/>
            <h1:Field Type="9902" Value="HAB"/>
            <h1:Field Type="9904" Value="Mark Schneider"/>
            <h1:Field Type="1903" Value="832"/>
            <h1:Block Type="t2" CreationDate="20.09.2024 09:10:37" ChangeDate="20.09.2024 09:10:37" FieldsCount="71">
                <h1:Field Type="5001" Value="93020464,INI"/>
                <h1:Field Type="5230" Value="Registereintrag"/>
                <h1:Field Type="4665" Value="10v"/>
                <h1:Field Type="5650" Value="Initium">
                    <h1:Field Type="5666l" Value="Abbatiae veteris Epternacensis cum opes et magnificentia"/>
                    <h1:Field Type="5680" Value="lateinisch"/>
                </h1:Field>
            </h1:Block>
            <h1:Block Type="t2" CreationDate="20.09.2024 09:10:37" ChangeDate="20.09.2024 09:10:37" FieldsCount="71">
                <h1:Field Type="5001" Value="93020465,INI"/>
                <h1:Field Type="5230" Value="Registereintrag"/>
                <h1:Field Type="4665" Value="18r"/>
                <h1:Field Type="5650" Value="Initium">
                    <h1:Field Type="5666l" Value="Anno sescentesimo nonagesimo pontificatus Romae sancti Sergii"/>
                    <h1:Field Type="5680" Value="lateinisch"/>
                </h1:Field>
            </h1:Block>
            <h1:Block Type="t2" CreationDate="20.09.2024 09:10:37" ChangeDate="20.09.2024 09:10:37" FieldsCount="71">
                <h1:Field Type="5001" Value="93020466,INI"/>
                <h1:Field Type="5230" Value="Registereintrag"/>
                <h1:Field Type="4665" Value="10r"/>
                <h1:Field Type="5650" Value="Initium">
                    <h1:Field Type="5666l" Value="Celeberrimus sancti Willibrordi cultus est Epternaci"/>
                    <h1:Field Type="5680" Value="lateinisch"/>
                </h1:Field>
            </h1:Block>
            <h1:Block Type="t2" CreationDate="20.09.2024 09:10:37" ChangeDate="20.09.2024 09:10:37" FieldsCount="71">
                <h1:Field Type="5001" Value="93020467,INI"/>
                <h1:Field Type="5230" Value="Registereintrag"/>
                <h1:Field Type="4665" Value="1r"/>
                <h1:Field Type="5650" Value="Initium">
                    <h1:Field Type="5666l" Value="Fundator monasterii Epternacensis exstitit sanctus Clemens Willibrordus Anglosaxo editus in lucem"/>
                    <h1:Field Type="5680" Value="lateinisch"/>
                </h1:Field>
            </h1:Block>
            <h1:Block Type="t2" CreationDate="20.09.2024 09:10:37" ChangeDate="20.09.2024 09:10:37" FieldsCount="71">
                <h1:Field Type="5001" Value="93020468,INI"/>
                <h1:Field Type="5230" Value="Registereintrag"/>
                <h1:Field Type="4665" Value="12v"/>
                <h1:Field Type="5650" Value="Initium">
                    <h1:Field Type="5666l" Value="Haec est primaeva fundatio abbatiae Epternacensis"/>
                    <h1:Field Type="5680" Value="lateinisch"/>
                </h1:Field>
            </h1:Block>
            <h1:Block Type="t2" CreationDate="20.09.2024 09:10:37" ChangeDate="20.09.2024 09:10:37" FieldsCount="71">
                <h1:Field Type="5001" Value="93020469,INI"/>
                <h1:Field Type="5230" Value="Registereintrag"/>
                <h1:Field Type="4665" Value="16v"/>
                <h1:Field Type="5650" Value="Initium">
                    <h1:Field Type="5666l" Value="Sed ut ad Epternacum redeamus postquam locum sacrum"/>
                    <h1:Field Type="5680" Value="lateinisch"/>
                </h1:Field>
            </h1:Block>
        </h1:Block>
    </h1:Document>
    <h1:Document DocKey="obj     93012928" FieldsCount="57">
        <h1:Block Type="obj" CreationDate="06.01.2022 14:23:17" CreatorID="Admin" ChangeDate="06.01.2022 14:23:17" ChangerID="Retro" OwnerID="Retro" FieldsCount="31">
            <h1:Field Type="5000" Value="93012928"/>
            <h1:Field Type="bezsoz" Value="Verwaltung">
                <h1:Field Type="4564" Value="Luxemburg (Stadt)"/>
                <h1:Field Type="4600" Value="Archives diocésaines de Luxembourg"/>
                <h1:Field Type="4500" Value="30003532"/>
                <h1:Field Type="4502norm" Value="1230022287"/>
                <h1:Field Type="4503norm" Value="LU-DAL"/>
                <h1:Field Type="4650" Value="Arch. Diocésaines, Pfarrarchiv Grevenmacher PA. Grevenmacher 21"/>
            </h1:Field>
            <h1:Field Type="4643" Value="Pfarrarchiv Grevenmacher"/>
            <h1:Field Type="4645" Value="PA. Grevenmacher 21"/>
            <h1:Field Type="5209vt" Value="Biblia Latina"/>
            <h1:Field Type="5209norm" Value="Biblia Latina (Fragm.)"/>
            <h1:Field Type="5230" Value="Handschrift"/>
            <h1:Field Type="5210norm" Value="vorhanden"/>
            <h1:Field Type="5240vt" Value="Fragment"/>
            <h1:Field Type="5240norm" Value="Fragment"/>
            <h1:Field Type="5060vt" Value="Datierung">
                <h1:Field Type="5064vt" Value="1051-1081"/>
            </h1:Field>
            <h1:Field Type="5060norm" Value="Datierung">
                <h1:Field Type="5064norm" Value="1051–1081"/>
                <h1:Field Type="5071norm" Value="1051"/>
                <h1:Field Type="5077norm" Value="1081"/>
            </h1:Field>
            <h1:Field Type="5130vt" Value="Echternach"/>
            <h1:Field Type="5130norm" Value="Echternach">
                <h1:Field Type="5131norm" Value="4013481-7"/>
                <h1:Field Type="5132norm" Value="2960630"/>
                <h1:Field Type="5133norm" Value="7012312"/>
            </h1:Field>
            <h1:Field Type="9951norm" Value="Beschreibung">
                <h1:Field Type="9952norm" Value="Thomas Falmagne"/>
                <h1:Field Type="9953norm" Value="2009"/>
            </h1:Field>
            <h1:Field Type="5260vt" Value="Pergament"/>
            <h1:Field Type="5260norm" Value="Pergament"/>
            <h1:Field Type="5360vt" Value="49 x 36 (cm)"/>
            <h1:Field Type="5360norm" Value="49 × 36">
                <h1:Field Type="5361norm" Value="49"/>
                <h1:Field Type="5362norm" Value="36"/>
                <h1:Field Type="5364norm" Value="real"/>
            </h1:Field>
            <h1:Field Type="5382norm" Value="&gt; Folio"/>
            <h1:Field Type="5706vt" Value="1 Einzelbl. (Blatt)"/>
            <h1:Field Type="5706norm" Value="1 Einzelbl."/>
            <h1:Field Type="5706rech" Value="1"/>
            <h1:Field Type="5710norm" Value="lateinisch"/>
            <h1:Field Type="bezlit" Value="Katalogtext">
                <h1:Field Type="8330" Value="Luxemburg BN Kat. 1.2"/>
            </h1:Field>
            <h1:Field Type="8265" Value="FALMAGNE, Thomas unter Mitwirkung von Luc DEITZ: Die Echternacher Handschriften bis zum Jahr 1628 in den Beständen der Bibliothèque Nationale de Luxembourg sowie der Archives diocésaines de Luxembourg, der Archives nationales, der Section historique de l'Institut grand-ducal und des Grand Séminaire de Luxembourg. Teil 2: Beschreibungen und Register. - Wiesbaden: Harrassowitz, 2009. - (Die Handschriften der Bibliothèque Nationale de Luxembourg; 1,2)"/>
            <h1:Field Type="8440norm" Value="Anfang">
                <h1:Field Type="8441norm" Value="543"/>
                <h1:Field Type="8442norm" Value="3"/>
                <h1:Field Type="8443norm" Value="Page543_Block3"/>
            </h1:Field>
            <h1:Field Type="8440norm" Value="Ende">
                <h1:Field Type="8441norm" Value="544"/>
                <h1:Field Type="8442norm" Value="4"/>
                <h1:Field Type="8443norm" Value="Page544_Block4"/>
            </h1:Field>
            <h1:Field Type="8450" Value="RETROKatalog">
                <h1:Field Type="8540" Value="LUX_DioezesanA_Kat_1_2"/>
            </h1:Field>
            <h1:Field Type="99hs" Value="Retrokonversionsdokument TEI"/>
            <h1:Field Type="1903" Value="832"/>
        </h1:Block>
    </h1:Document>
</h1:DocumentSet>
